[{"id": 1186584, "card1": "A", "card2": "A", "card3": "3", "card4": "2", "doubleSuited": false, "goodSuit": false, "fold": 0.0, "call": 0.0, "raise": 0.5, "raiseCallIP": 0.5, "raiseCallOP": 0.5}, {"id": 1186587, "card1": "A", "card2": "A", "card3": "3", "card4": "2", "doubleSuited": false, "goodSuit": true, "fold": 0.0, "call": 0.0, "raise": 0.5, "raiseCallIP": 0.5, "raiseCallOP": 0.5}, {"id": 1186685, "card1": "A", "card2": "A", "card3": "2", "card4": "2", "doubleSuited": false, "goodSuit": true, "fold": 0.0, "call": 0.0, "raise": 0.25, "raiseCallIP": 0.25, "raiseCallOP": 0.25}, {"id": 1186713, "card1": "A", "card2": "A", "card3": "4", "card4": "2", "doubleSuited": false, "goodSuit": false, "fold": 0.0, "call": 0.0, "raise": 0.5, "raiseCallIP": 0.5, "raiseCallOP": 0.5}, {"id": 1186717, "card1": "A", "card2": "A", "card3": "4", "card4": "2", "doubleSuited": false, "goodSuit": true, "fold": 0.0, "call": 0.0, "raise": 0.5, "raiseCallIP": 0.5, "raiseCallOP": 0.5}, {"id": 1186745, "card1": "A", "card2": "A", "card3": "4", "card4": "3", "doubleSuited": false, "goodSuit": false, "fold": 0.0, "call": 0.0, "raise": 0.5, "raiseCallIP": 0.5, "raiseCallOP": 0.5}, {"id": 1186749, "card1": "A", "card2": "A", "card3": "4", "card4": "3", "doubleSuited": false, "goodSuit": true, "fold": 0.0, "call": 0.0, "raise": 0.5, "raiseCallIP": 0.5, "raiseCallOP": 0.5}, {"id": 1186945, "card1": "A", "card2": "A", "card3": "3", "card4": "3", "doubleSuited": false, "goodSuit": true, "fold": 0.0, "call": 0.0, "raise": 0.25, "raiseCallIP": 0.25, "raiseCallOP": 0.25}, {"id": 1186957, "card1": "A", "card2": "A", "card3": "5", "card4": "3", "doubleSuited": false, "goodSuit": false, "fold": 0.0, "call": 0.0, "raise": 0.5, "raiseCallIP": 0.5, "raiseCallOP": 0.5}, {"id": 1186960, "card1": "A", "card2": "A", "card3": "5", "card4": "3", "doubleSuited": false, "goodSuit": true, "fold": 0.0, "call": 0.0, "raise": 0.5, "raiseCallIP": 0.5, "raiseCallOP": 0.5}, {"id": 1186985, "card1": "A", "card2": "A", "card3": "5", "card4": "4", "doubleSuited": false, "goodSuit": false, "fold": 0.0, "call": 0.0, "raise": 0.5, "raiseCallIP": 0.5, "raiseCallOP": 0.5}, {"id": 1186987, "card1": "A", "card2": "A", "card3": "5", "card4": "4", "doubleSuited": false, "goodSuit": true, "fold": 0.0, "call": 0.0, "raise": 0.5, "raiseCallIP": 0.5, "raiseCallOP": 0.5}, {"id": 1186996, "card1": "A", "card2": "A", "card3": "5", "card4": "2", "doubleSuited": false, "goodSuit": false, "fold": 0.0, "call": 0.0, "raise": 0.5, "raiseCallIP": 0.5, "raiseCallOP": 0.5}, {"id": 1187001, "card1": "A", "card2": "A", "card3": "5", "card4": "2", "doubleSuited": false, "goodSuit": true, "fold": 0.0, "call": 0.0, "raise": 0.5, "raiseCallIP": 0.5, "raiseCallOP": 0.5}, {"id": 1187101, "card1": "A", "card2": "A", "card3": "4", "card4": "4", "doubleSuited": false, "goodSuit": true, "fold": 0.0, "call": 0.0, "raise": 0.25, "raiseCallIP": 0.25, "raiseCallOP": 0.25}, {"id": 1187125, "card1": "A", "card2": "A", "card3": "6", "card4": "4", "doubleSuited": false, "goodSuit": false, "fold": 0.0, "call": 0.0, "raise": 0.5, "raiseCallIP": 0.5, "raiseCallOP": 0.5}, {"id": 1187129, "card1": "A", "card2": "A", "card3": "6", "card4": "4", "doubleSuited": false, "goodSuit": true, "fold": 0.0, "call": 0.0, "raise": 0.5, "raiseCallIP": 0.5, "raiseCallOP": 0.5}, {"id": 1187138, "card1": "A", "card2": "A", "card3": "6", "card4": "5", "doubleSuited": false, "goodSuit": false, "fold": 0.0, "call": 0.0, "raise": 0.5, "raiseCallIP": 0.5, "raiseCallOP": 0.5}, {"id": 1187141, "card1": "A", "card2": "A", "card3": "6", "card4": "5", "doubleSuited": false, "goodSuit": true, "fold": 0.0, "call": 0.0, "raise": 0.5, "raiseCallIP": 0.5, "raiseCallOP": 0.5}, {"id": 1187152, "card1": "A", "card2": "A", "card3": "6", "card4": "2", "doubleSuited": false, "goodSuit": false, "fold": 0.0, "call": 0.0, "raise": 0.5, "raiseCallIP": 0.5, "raiseCallOP": 0.5}, {"id": 1187156, "card1": "A", "card2": "A", "card3": "6", "card4": "2", "doubleSuited": false, "goodSuit": true, "fold": 0.0, "call": 0.0, "raise": 0.5, "raiseCallIP": 0.5, "raiseCallOP": 0.5}, {"id": 1187164, "card1": "A", "card2": "A", "card3": "6", "card4": "3", "doubleSuited": false, "goodSuit": false, "fold": 0.0, "call": 0.0, "raise": 0.5, "raiseCallIP": 0.5, "raiseCallOP": 0.5}, {"id": 1187169, "card1": "A", "card2": "A", "card3": "6", "card4": "3", "doubleSuited": false, "goodSuit": true, "fold": 0.0, "call": 0.0, "raise": 0.5, "raiseCallIP": 0.5, "raiseCallOP": 0.5}, {"id": 1187229, "card1": "A", "card2": "A", "card3": "5", "card4": "5", "doubleSuited": false, "goodSuit": true, "fold": 0.0, "call": 0.0, "raise": 0.25, "raiseCallIP": 0.25, "raiseCallOP": 0.25}, {"id": 1187239, "card1": "A", "card2": "A", "card3": "7", "card4": "5", "doubleSuited": false, "goodSuit": false, "fold": 0.0, "call": 1e-06, "raise": 0.499999, "raiseCallIP": 0.499999, "raiseCallOP": 0.499999}, {"id": 1187243, "card1": "A", "card2": "A", "card3": "7", "card4": "5", "doubleSuited": false, "goodSuit": true, "fold": 0.0, "call": 0.0, "raise": 0.5, "raiseCallIP": 0.5, "raiseCallOP": 0.5}, {"id": 1187255, "card1": "A", "card2": "A", "card3": "7", "card4": "6", "doubleSuited": false, "goodSuit": false, "fold": 0.0, "call": 0.0, "raise": 0.5, "raiseCallIP": 0.5, "raiseCallOP": 0.5}, {"id": 1187258, "card1": "A", "card2": "A", "card3": "7", "card4": "6", "doubleSuited": false, "goodSuit": true, "fold": 0.0, "call": 0.0, "raise": 0.5, "raiseCallIP": 0.5, "raiseCallOP": 0.5}, {"id": 1187277, "card1": "A", "card2": "A", "card3": "7", "card4": "3", "doubleSuited": false, "goodSuit": false, "fold": 0.0, "call": 0.0, "raise": 0.5, "raiseCallIP": 0.5, "raiseCallOP": 0.5}, {"id": 1187281, "card1": "A", "card2": "A", "card3": "7", "card4": "3", "doubleSuited": false, "goodSuit": true, "fold": 0.0, "call": 0.0, "raise": 0.5, "raiseCallIP": 0.5, "raiseCallOP": 0.5}, {"id": 1187290, "card1": "A", "card2": "A", "card3": "7", "card4": "4", "doubleSuited": false, "goodSuit": false, "fold": 0.0, "call": 0.0, "raise": 0.5, "raiseCallIP": 0.5, "raiseCallOP": 0.5}, {"id": 1187294, "card1": "A", "card2": "A", "card3": "7", "card4": "4", "doubleSuited": false, "goodSuit": true, "fold": 0.0, "call": 0.0, "raise": 0.5, "raiseCallIP": 0.5, "raiseCallOP": 0.5}, {"id": 1187302, "card1": "A", "card2": "A", "card3": "7", "card4": "2", "doubleSuited": false, "goodSuit": false, "fold": 0.0, "call": 0.0, "raise": 0.5, "raiseCallIP": 0.5, "raiseCallOP": 0.5}, {"id": 1187306, "card1": "A", "card2": "A", "card3": "7", "card4": "2", "doubleSuited": false, "goodSuit": true, "fold": 0.0, "call": 0.0, "raise": 0.5, "raiseCallIP": 0.5, "raiseCallOP": 0.5}, {"id": 1187405, "card1": "A", "card2": "A", "card3": "6", "card4": "6", "doubleSuited": false, "goodSuit": true, "fold": 0.0, "call": 0.0, "raise": 0.25, "raiseCallIP": 0.25, "raiseCallOP": 0.25}, {"id": 1187428, "card1": "A", "card2": "A", "card3": "8", "card4": "6", "doubleSuited": false, "goodSuit": false, "fold": 0.0, "call": 0.0, "raise": 0.5, "raiseCallIP": 0.5, "raiseCallOP": 0.5}, {"id": 1187432, "card1": "A", "card2": "A", "card3": "8", "card4": "6", "doubleSuited": false, "goodSuit": true, "fold": 0.0, "call": 0.0, "raise": 0.5, "raiseCallIP": 0.5, "raiseCallOP": 0.5}, {"id": 1187458, "card1": "A", "card2": "A", "card3": "8", "card4": "7", "doubleSuited": false, "goodSuit": false, "fold": 0.0, "call": 0.0, "raise": 0.5, "raiseCallIP": 0.5, "raiseCallOP": 0.5}, {"id": 1187461, "card1": "A", "card2": "A", "card3": "8", "card4": "7", "doubleSuited": false, "goodSuit": true, "fold": 0.0, "call": 0.0, "raise": 0.5, "raiseCallIP": 0.5, "raiseCallOP": 0.5}, {"id": 1187470, "card1": "A", "card2": "A", "card3": "8", "card4": "4", "doubleSuited": false, "goodSuit": false, "fold": 0.0, "call": 0.0, "raise": 0.5, "raiseCallIP": 0.5, "raiseCallOP": 0.5}, {"id": 1187474, "card1": "A", "card2": "A", "card3": "8", "card4": "4", "doubleSuited": false, "goodSuit": true, "fold": 0.0, "call": 0.0, "raise": 0.5, "raiseCallIP": 0.5, "raiseCallOP": 0.5}, {"id": 1187484, "card1": "A", "card2": "A", "card3": "8", "card4": "5", "doubleSuited": false, "goodSuit": false, "fold": 0.0, "call": 0.0, "raise": 0.5, "raiseCallIP": 0.5, "raiseCallOP": 0.5}, {"id": 1187487, "card1": "A", "card2": "A", "card3": "8", "card4": "5", "doubleSuited": false, "goodSuit": true, "fold": 0.0, "call": 0.0, "raise": 0.5, "raiseCallIP": 0.5, "raiseCallOP": 0.5}, {"id": 1187497, "card1": "A", "card2": "A", "card3": "8", "card4": "2", "doubleSuited": false, "goodSuit": false, "fold": 0.0, "call": 0.0, "raise": 0.5, "raiseCallIP": 0.5, "raiseCallOP": 0.5}, {"id": 1187501, "card1": "A", "card2": "A", "card3": "8", "card4": "2", "doubleSuited": false, "goodSuit": true, "fold": 0.0, "call": 0.0, "raise": 0.5, "raiseCallIP": 0.5, "raiseCallOP": 0.5}, {"id": 1187509, "card1": "A", "card2": "A", "card3": "8", "card4": "3", "doubleSuited": false, "goodSuit": false, "fold": 0.0, "call": 0.0, "raise": 0.5, "raiseCallIP": 0.5, "raiseCallOP": 0.5}, {"id": 1187512, "card1": "A", "card2": "A", "card3": "8", "card4": "3", "doubleSuited": false, "goodSuit": true, "fold": 0.0, "call": 0.0, "raise": 0.5, "raiseCallIP": 0.5, "raiseCallOP": 0.5}, {"id": 1187588, "card1": "A", "card2": "A", "card3": "7", "card4": "7", "doubleSuited": false, "goodSuit": true, "fold": 0.0, "call": 0.0, "raise": 0.25, "raiseCallIP": 0.25, "raiseCallOP": 0.25}, {"id": 1187615, "card1": "A", "card2": "A", "card3": "9", "card4": "7", "doubleSuited": false, "goodSuit": false, "fold": 0.0, "call": 0.0, "raise": 0.5, "raiseCallIP": 0.5, "raiseCallOP": 0.5}, {"id": 1187619, "card1": "A", "card2": "A", "card3": "9", "card4": "7", "doubleSuited": false, "goodSuit": true, "fold": 0.0, "call": 0.0, "raise": 0.5, "raiseCallIP": 0.5, "raiseCallOP": 0.5}, {"id": 1187645, "card1": "A", "card2": "A", "card3": "9", "card4": "8", "doubleSuited": false, "goodSuit": false, "fold": 0.0, "call": 0.0, "raise": 0.5, "raiseCallIP": 0.5, "raiseCallOP": 0.5}, {"id": 1187648, "card1": "A", "card2": "A", "card3": "9", "card4": "8", "doubleSuited": false, "goodSuit": true, "fold": 0.0, "call": 0.0, "raise": 0.5, "raiseCallIP": 0.5, "raiseCallOP": 0.5}, {"id": 1187657, "card1": "A", "card2": "A", "card3": "9", "card4": "5", "doubleSuited": false, "goodSuit": false, "fold": 0.0, "call": 0.0, "raise": 0.5, "raiseCallIP": 0.5, "raiseCallOP": 0.5}, {"id": 1187661, "card1": "A", "card2": "A", "card3": "9", "card4": "5", "doubleSuited": false, "goodSuit": true, "fold": 0.0, "call": 0.0, "raise": 0.5, "raiseCallIP": 0.5, "raiseCallOP": 0.5}, {"id": 1187678, "card1": "A", "card2": "A", "card3": "9", "card4": "6", "doubleSuited": false, "goodSuit": false, "fold": 0.0, "call": 0.0, "raise": 0.5, "raiseCallIP": 0.5, "raiseCallOP": 0.5}, {"id": 1187682, "card1": "A", "card2": "A", "card3": "9", "card4": "6", "doubleSuited": false, "goodSuit": true, "fold": 0.0, "call": 0.0, "raise": 0.5, "raiseCallIP": 0.5, "raiseCallOP": 0.5}, {"id": 1187691, "card1": "A", "card2": "A", "card3": "9", "card4": "3", "doubleSuited": false, "goodSuit": false, "fold": 0.0, "call": 0.0, "raise": 0.5, "raiseCallIP": 0.5, "raiseCallOP": 0.5}, {"id": 1187694, "card1": "A", "card2": "A", "card3": "9", "card4": "3", "doubleSuited": false, "goodSuit": true, "fold": 0.0, "call": 0.0, "raise": 0.5, "raiseCallIP": 0.5, "raiseCallOP": 0.5}, {"id": 1187704, "card1": "A", "card2": "A", "card3": "9", "card4": "4", "doubleSuited": false, "goodSuit": false, "fold": 0.0, "call": 0.0, "raise": 0.5, "raiseCallIP": 0.5, "raiseCallOP": 0.5}, {"id": 1187708, "card1": "A", "card2": "A", "card3": "9", "card4": "4", "doubleSuited": false, "goodSuit": true, "fold": 0.0, "call": 0.0, "raise": 0.5, "raiseCallIP": 0.5, "raiseCallOP": 0.5}, {"id": 1187718, "card1": "A", "card2": "A", "card3": "9", "card4": "2", "doubleSuited": false, "goodSuit": false, "fold": 0.0, "call": 0.0, "raise": 0.5, "raiseCallIP": 0.5, "raiseCallOP": 0.5}, {"id": 1187721, "card1": "A", "card2": "A", "card3": "9", "card4": "2", "doubleSuited": false, "goodSuit": true, "fold": 0.0, "call": 0.0, "raise": 0.5, "raiseCallIP": 0.5, "raiseCallOP": 0.5}, {"id": 1187816, "card1": "A", "card2": "A", "card3": "8", "card4": "8", "doubleSuited": false, "goodSuit": true, "fold": 0.0, "call": 0.0, "raise": 0.25, "raiseCallIP": 0.25, "raiseCallOP": 0.25}, {"id": 1187880, "card1": "A", "card2": "A", "card3": "9", "card4": "9", "doubleSuited": false, "goodSuit": true, "fold": 0.0, "call": 0.0, "raise": 0.25, "raiseCallIP": 0.25, "raiseCallOP": 0.25}, {"id": 1189007, "card1": "A", "card2": "A", "card3": "A", "card4": "9", "doubleSuited": false, "goodSuit": true, "fold": 0.0, "call": 0.0, "raise": 0.166667, "raiseCallIP": 0.166667, "raiseCallOP": 0.166667}, {"id": 1189030, "card1": "A", "card2": "A", "card3": "A", "card4": "7", "doubleSuited": false, "goodSuit": true, "fold": 3e-06, "call": 1e-06, "raise": 0.166663, "raiseCallIP": 0.166663, "raiseCallOP": 0.166663}, {"id": 1189036, "card1": "A", "card2": "A", "card3": "A", "card4": "8", "doubleSuited": false, "goodSuit": true, "fold": 0.0, "call": 0.0, "raise": 0.166666, "raiseCallIP": 0.166666, "raiseCallOP": 0.166666}, {"id": 1189042, "card1": "A", "card2": "A", "card3": "A", "card4": "5", "doubleSuited": false, "goodSuit": true, "fold": 1e-06, "call": 1e-06, "raise": 0.166665, "raiseCallIP": 0.166665, "raiseCallOP": 0.166665}, {"id": 1189049, "card1": "A", "card2": "A", "card3": "A", "card4": "6", "doubleSuited": false, "goodSuit": true, "fold": 7e-06, "call": 0.0, "raise": 0.166659, "raiseCallIP": 0.166659, "raiseCallOP": 0.166659}, {"id": 1189053, "card1": "A", "card2": "A", "card3": "A", "card4": "3", "doubleSuited": false, "goodSuit": true, "fold": 0.0, "call": 0.0, "raise": 0.166666, "raiseCallIP": 0.166666, "raiseCallOP": 0.166666}, {"id": 1189059, "card1": "A", "card2": "A", "card3": "A", "card4": "4", "doubleSuited": false, "goodSuit": true, "fold": 1e-06, "call": 2e-06, "raise": 0.166664, "raiseCallIP": 0.166664, "raiseCallOP": 0.166664}, {"id": 1189066, "card1": "A", "card2": "A", "card3": "A", "card4": "2", "doubleSuited": false, "goodSuit": true, "fold": 0.0, "call": 0.0, "raise": 0.166667, "raiseCallIP": 0.166667, "raiseCallOP": 0.166667}, {"id": 1189253, "card1": "A", "card2": "A", "card3": "A", "card4": "T", "doubleSuited": false, "goodSuit": true, "fold": 1e-06, "call": 0.0, "raise": 0.166666, "raiseCallIP": 0.166666, "raiseCallOP": 0.166666}, {"id": 1189275, "card1": "A", "card2": "A", "card3": "A", "card4": "Q", "doubleSuited": false, "goodSuit": true, "fold": 0.0, "call": 0.0, "raise": 0.166667, "raiseCallIP": 0.166667, "raiseCallOP": 0.166667}, {"id": 1189353, "card1": "A", "card2": "A", "card3": "A", "card4": "K", "doubleSuited": false, "goodSuit": true, "fold": 0.0, "call": 0.0, "raise": 0.166666, "raiseCallIP": 0.166666, "raiseCallOP": 0.166666}, {"id": 1189403, "card1": "A", "card2": "A", "card3": "A", "card4": "J", "doubleSuited": false, "goodSuit": true, "fold": 3e-06, "call": 1e-06, "raise": 0.166663, "raiseCallIP": 0.166663, "raiseCallOP": 0.166663}, {"id": 1191817, "card1": "A", "card2": "A", "card3": "J", "card4": "8", "doubleSuited": false, "goodSuit": false, "fold": 0.0, "call": 0.0, "raise": 0.5, "raiseCallIP": 0.5, "raiseCallOP": 0.5}, {"id": 1191820, "card1": "A", "card2": "A", "card3": "J", "card4": "8", "doubleSuited": false, "goodSuit": true, "fold": 0.0, "call": 0.0, "raise": 0.5, "raiseCallIP": 0.5, "raiseCallOP": 0.5}, {"id": 1191842, "card1": "A", "card2": "A", "card3": "J", "card4": "9", "doubleSuited": false, "goodSuit": false, "fold": 0.0, "call": 0.0, "raise": 0.5, "raiseCallIP": 0.5, "raiseCallOP": 0.5}, {"id": 1191844, "card1": "A", "card2": "A", "card3": "J", "card4": "9", "doubleSuited": false, "goodSuit": true, "fold": 0.0, "call": 0.0, "raise": 0.5, "raiseCallIP": 0.5, "raiseCallOP": 0.5}, {"id": 1191864, "card1": "A", "card2": "A", "card3": "J", "card4": "6", "doubleSuited": false, "goodSuit": false, "fold": 0.0, "call": 0.0, "raise": 0.5, "raiseCallIP": 0.5, "raiseCallOP": 0.5}, {"id": 1191868, "card1": "A", "card2": "A", "card3": "J", "card4": "6", "doubleSuited": false, "goodSuit": true, "fold": 0.0, "call": 0.0, "raise": 0.5, "raiseCallIP": 0.5, "raiseCallOP": 0.5}, {"id": 1191875, "card1": "A", "card2": "A", "card3": "J", "card4": "7", "doubleSuited": false, "goodSuit": false, "fold": 0.0, "call": 0.0, "raise": 0.5, "raiseCallIP": 0.5, "raiseCallOP": 0.5}, {"id": 1191878, "card1": "A", "card2": "A", "card3": "J", "card4": "7", "doubleSuited": false, "goodSuit": true, "fold": 0.0, "call": 0.0, "raise": 0.5, "raiseCallIP": 0.5, "raiseCallOP": 0.5}, {"id": 1191888, "card1": "A", "card2": "A", "card3": "J", "card4": "4", "doubleSuited": false, "goodSuit": false, "fold": 0.0, "call": 0.0, "raise": 0.5, "raiseCallIP": 0.5, "raiseCallOP": 0.5}, {"id": 1191890, "card1": "A", "card2": "A", "card3": "J", "card4": "4", "doubleSuited": false, "goodSuit": true, "fold": 0.0, "call": 0.0, "raise": 0.5, "raiseCallIP": 0.5, "raiseCallOP": 0.5}, {"id": 1191912, "card1": "A", "card2": "A", "card3": "J", "card4": "5", "doubleSuited": false, "goodSuit": false, "fold": 0.0, "call": 0.0, "raise": 0.5, "raiseCallIP": 0.5, "raiseCallOP": 0.5}, {"id": 1191915, "card1": "A", "card2": "A", "card3": "J", "card4": "5", "doubleSuited": false, "goodSuit": true, "fold": 0.0, "call": 0.0, "raise": 0.5, "raiseCallIP": 0.5, "raiseCallOP": 0.5}, {"id": 1191935, "card1": "A", "card2": "A", "card3": "J", "card4": "2", "doubleSuited": false, "goodSuit": false, "fold": 0.0, "call": 0.0, "raise": 0.5, "raiseCallIP": 0.5, "raiseCallOP": 0.5}, {"id": 1191939, "card1": "A", "card2": "A", "card3": "J", "card4": "2", "doubleSuited": false, "goodSuit": true, "fold": 0.0, "call": 0.0, "raise": 0.5, "raiseCallIP": 0.5, "raiseCallOP": 0.5}, {"id": 1191960, "card1": "A", "card2": "A", "card3": "J", "card4": "3", "doubleSuited": false, "goodSuit": false, "fold": 0.0, "call": 0.0, "raise": 0.5, "raiseCallIP": 0.5, "raiseCallOP": 0.5}, {"id": 1191963, "card1": "A", "card2": "A", "card3": "J", "card4": "3", "doubleSuited": false, "goodSuit": true, "fold": 0.0, "call": 0.0, "raise": 0.5, "raiseCallIP": 0.5, "raiseCallOP": 0.5}, {"id": 1192071, "card1": "A", "card2": "A", "card3": "K", "card4": "J", "doubleSuited": false, "goodSuit": false, "fold": 0.0, "call": 0.0, "raise": 0.5, "raiseCallIP": 0.5, "raiseCallOP": 0.5}, {"id": 1192074, "card1": "A", "card2": "A", "card3": "K", "card4": "J", "doubleSuited": false, "goodSuit": true, "fold": 0.0, "call": 0.0, "raise": 0.5, "raiseCallIP": 0.5, "raiseCallOP": 0.5}, {"id": 1192162, "card1": "A", "card2": "A", "card3": "K", "card4": "9", "doubleSuited": false, "goodSuit": false, "fold": 0.0, "call": 0.0, "raise": 0.5, "raiseCallIP": 0.5, "raiseCallOP": 0.5}, {"id": 1192165, "card1": "A", "card2": "A", "card3": "K", "card4": "9", "doubleSuited": false, "goodSuit": true, "fold": 0.0, "call": 0.0, "raise": 0.5, "raiseCallIP": 0.5, "raiseCallOP": 0.5}, {"id": 1192174, "card1": "A", "card2": "A", "card3": "K", "card4": "7", "doubleSuited": false, "goodSuit": false, "fold": 0.0, "call": 0.0, "raise": 0.5, "raiseCallIP": 0.5, "raiseCallOP": 0.5}, {"id": 1192177, "card1": "A", "card2": "A", "card3": "K", "card4": "7", "doubleSuited": false, "goodSuit": true, "fold": 0.0, "call": 0.0, "raise": 0.5, "raiseCallIP": 0.5, "raiseCallOP": 0.5}, {"id": 1192184, "card1": "A", "card2": "A", "card3": "K", "card4": "8", "doubleSuited": false, "goodSuit": false, "fold": 0.0, "call": 0.0, "raise": 0.5, "raiseCallIP": 0.5, "raiseCallOP": 0.5}, {"id": 1192188, "card1": "A", "card2": "A", "card3": "K", "card4": "8", "doubleSuited": false, "goodSuit": true, "fold": 0.0, "call": 0.0, "raise": 0.5, "raiseCallIP": 0.5, "raiseCallOP": 0.5}, {"id": 1192198, "card1": "A", "card2": "A", "card3": "K", "card4": "5", "doubleSuited": false, "goodSuit": false, "fold": 0.0, "call": 0.0, "raise": 0.5, "raiseCallIP": 0.5, "raiseCallOP": 0.5}, {"id": 1192202, "card1": "A", "card2": "A", "card3": "K", "card4": "5", "doubleSuited": false, "goodSuit": true, "fold": 0.0, "call": 0.0, "raise": 0.5, "raiseCallIP": 0.5, "raiseCallOP": 0.5}, {"id": 1192208, "card1": "A", "card2": "A", "card3": "J", "card4": "T", "doubleSuited": false, "goodSuit": false, "fold": 0.0, "call": 0.0, "raise": 0.5, "raiseCallIP": 0.5, "raiseCallOP": 0.5}, {"id": 1192211, "card1": "A", "card2": "A", "card3": "J", "card4": "T", "doubleSuited": false, "goodSuit": true, "fold": 0.0, "call": 0.0, "raise": 0.5, "raiseCallIP": 0.5, "raiseCallOP": 0.5}, {"id": 1192219, "card1": "A", "card2": "A", "card3": "K", "card4": "6", "doubleSuited": false, "goodSuit": false, "fold": 0.0, "call": 0.0, "raise": 0.5, "raiseCallIP": 0.5, "raiseCallOP": 0.5}, {"id": 1192222, "card1": "A", "card2": "A", "card3": "K", "card4": "6", "doubleSuited": false, "goodSuit": true, "fold": 0.0, "call": 0.0, "raise": 0.5, "raiseCallIP": 0.5, "raiseCallOP": 0.5}, {"id": 1192231, "card1": "A", "card2": "A", "card3": "K", "card4": "3", "doubleSuited": false, "goodSuit": false, "fold": 0.0, "call": 0.0, "raise": 0.5, "raiseCallIP": 0.5, "raiseCallOP": 0.5}, {"id": 1192234, "card1": "A", "card2": "A", "card3": "K", "card4": "3", "doubleSuited": false, "goodSuit": true, "fold": 0.0, "call": 0.0, "raise": 0.5, "raiseCallIP": 0.5, "raiseCallOP": 0.5}, {"id": 1192244, "card1": "A", "card2": "A", "card3": "K", "card4": "4", "doubleSuited": false, "goodSuit": false, "fold": 0.0, "call": 0.0, "raise": 0.5, "raiseCallIP": 0.5, "raiseCallOP": 0.5}, {"id": 1192246, "card1": "A", "card2": "A", "card3": "K", "card4": "4", "doubleSuited": false, "goodSuit": true, "fold": 0.0, "call": 0.0, "raise": 0.5, "raiseCallIP": 0.5, "raiseCallOP": 0.5}, {"id": 1192255, "card1": "A", "card2": "A", "card3": "K", "card4": "2", "doubleSuited": false, "goodSuit": false, "fold": 0.0, "call": 0.0, "raise": 0.5, "raiseCallIP": 0.5, "raiseCallOP": 0.5}, {"id": 1192258, "card1": "A", "card2": "A", "card3": "K", "card4": "2", "doubleSuited": false, "goodSuit": true, "fold": 0.0, "call": 0.0, "raise": 0.5, "raiseCallIP": 0.5, "raiseCallOP": 0.5}, {"id": 1192264, "card1": "A", "card2": "A", "card3": "J", "card4": "J", "doubleSuited": false, "goodSuit": true, "fold": 0.0, "call": 0.0, "raise": 0.25, "raiseCallIP": 0.25, "raiseCallOP": 0.25}, {"id": 1192343, "card1": "A", "card2": "A", "card3": "K", "card4": "T", "doubleSuited": false, "goodSuit": false, "fold": 0.0, "call": 0.0, "raise": 0.5, "raiseCallIP": 0.5, "raiseCallOP": 0.5}, {"id": 1192347, "card1": "A", "card2": "A", "card3": "K", "card4": "T", "doubleSuited": false, "goodSuit": true, "fold": 0.0, "call": 0.0, "raise": 0.5, "raiseCallIP": 0.5, "raiseCallOP": 0.5}, {"id": 1192369, "card1": "A", "card2": "A", "card3": "K", "card4": "Q", "doubleSuited": false, "goodSuit": false, "fold": 0.0, "call": 0.0, "raise": 0.5, "raiseCallIP": 0.5, "raiseCallOP": 0.5}, {"id": 1192372, "card1": "A", "card2": "A", "card3": "K", "card4": "Q", "doubleSuited": false, "goodSuit": true, "fold": 0.0, "call": 0.0, "raise": 0.5, "raiseCallIP": 0.5, "raiseCallOP": 0.5}, {"id": 1192427, "card1": "A", "card2": "A", "card3": "K", "card4": "K", "doubleSuited": false, "goodSuit": true, "fold": 0.0, "call": 0.0, "raise": 0.25, "raiseCallIP": 0.25, "raiseCallOP": 0.25}, {"id": 1193019, "card1": "A", "card2": "A", "card3": "Q", "card4": "J", "doubleSuited": false, "goodSuit": false, "fold": 0.0, "call": 0.0, "raise": 0.5, "raiseCallIP": 0.5, "raiseCallOP": 0.5}, {"id": 1193023, "card1": "A", "card2": "A", "card3": "Q", "card4": "J", "doubleSuited": false, "goodSuit": true, "fold": 0.0, "call": 0.0, "raise": 0.5, "raiseCallIP": 0.5, "raiseCallOP": 0.5}, {"id": 1193045, "card1": "A", "card2": "A", "card3": "Q", "card4": "9", "doubleSuited": false, "goodSuit": false, "fold": 0.0, "call": 0.0, "raise": 0.5, "raiseCallIP": 0.5, "raiseCallOP": 0.5}, {"id": 1193048, "card1": "A", "card2": "A", "card3": "Q", "card4": "9", "doubleSuited": false, "goodSuit": true, "fold": 0.0, "call": 0.0, "raise": 0.5, "raiseCallIP": 0.5, "raiseCallOP": 0.5}, {"id": 1193057, "card1": "A", "card2": "A", "card3": "Q", "card4": "7", "doubleSuited": false, "goodSuit": false, "fold": 0.0, "call": 0.0, "raise": 0.5, "raiseCallIP": 0.5, "raiseCallOP": 0.5}, {"id": 1193060, "card1": "A", "card2": "A", "card3": "Q", "card4": "7", "doubleSuited": false, "goodSuit": true, "fold": 0.0, "call": 0.0, "raise": 0.5, "raiseCallIP": 0.5, "raiseCallOP": 0.5}, {"id": 1193068, "card1": "A", "card2": "A", "card3": "Q", "card4": "8", "doubleSuited": false, "goodSuit": false, "fold": 0.0, "call": 0.0, "raise": 0.5, "raiseCallIP": 0.5, "raiseCallOP": 0.5}, {"id": 1193071, "card1": "A", "card2": "A", "card3": "Q", "card4": "8", "doubleSuited": false, "goodSuit": true, "fold": 0.0, "call": 0.0, "raise": 0.5, "raiseCallIP": 0.5, "raiseCallOP": 0.5}, {"id": 1193080, "card1": "A", "card2": "A", "card3": "Q", "card4": "5", "doubleSuited": false, "goodSuit": false, "fold": 0.0, "call": 0.0, "raise": 0.5, "raiseCallIP": 0.5, "raiseCallOP": 0.5}, {"id": 1193082, "card1": "A", "card2": "A", "card3": "Q", "card4": "5", "doubleSuited": false, "goodSuit": true, "fold": 0.0, "call": 0.0, "raise": 0.5, "raiseCallIP": 0.5, "raiseCallOP": 0.5}, {"id": 1193092, "card1": "A", "card2": "A", "card3": "Q", "card4": "6", "doubleSuited": false, "goodSuit": false, "fold": 0.0, "call": 0.0, "raise": 0.5, "raiseCallIP": 0.5, "raiseCallOP": 0.5}, {"id": 1193094, "card1": "A", "card2": "A", "card3": "Q", "card4": "6", "doubleSuited": false, "goodSuit": true, "fold": 0.0, "call": 0.0, "raise": 0.5, "raiseCallIP": 0.5, "raiseCallOP": 0.5}, {"id": 1193104, "card1": "A", "card2": "A", "card3": "Q", "card4": "3", "doubleSuited": false, "goodSuit": false, "fold": 0.0, "call": 0.0, "raise": 0.5, "raiseCallIP": 0.5, "raiseCallOP": 0.5}, {"id": 1193107, "card1": "A", "card2": "A", "card3": "Q", "card4": "3", "doubleSuited": false, "goodSuit": true, "fold": 0.0, "call": 0.0, "raise": 0.5, "raiseCallIP": 0.5, "raiseCallOP": 0.5}, {"id": 1193115, "card1": "A", "card2": "A", "card3": "Q", "card4": "4", "doubleSuited": false, "goodSuit": false, "fold": 0.0, "call": 0.0, "raise": 0.5, "raiseCallIP": 0.5, "raiseCallOP": 0.5}, {"id": 1193117, "card1": "A", "card2": "A", "card3": "Q", "card4": "4", "doubleSuited": false, "goodSuit": true, "fold": 0.0, "call": 0.0, "raise": 0.5, "raiseCallIP": 0.5, "raiseCallOP": 0.5}, {"id": 1193128, "card1": "A", "card2": "A", "card3": "Q", "card4": "2", "doubleSuited": false, "goodSuit": false, "fold": 0.0, "call": 0.0, "raise": 0.5, "raiseCallIP": 0.5, "raiseCallOP": 0.5}, {"id": 1193131, "card1": "A", "card2": "A", "card3": "Q", "card4": "2", "doubleSuited": false, "goodSuit": true, "fold": 0.0, "call": 0.0, "raise": 0.5, "raiseCallIP": 0.5, "raiseCallOP": 0.5}, {"id": 1193172, "card1": "A", "card2": "A", "card3": "Q", "card4": "T", "doubleSuited": false, "goodSuit": false, "fold": 0.0, "call": 0.0, "raise": 0.5, "raiseCallIP": 0.5, "raiseCallOP": 0.5}, {"id": 1193175, "card1": "A", "card2": "A", "card3": "Q", "card4": "T", "doubleSuited": false, "goodSuit": true, "fold": 0.0, "call": 0.0, "raise": 0.5, "raiseCallIP": 0.5, "raiseCallOP": 0.5}, {"id": 1193183, "card1": "A", "card2": "A", "card3": "Q", "card4": "Q", "doubleSuited": false, "goodSuit": true, "fold": 0.0, "call": 0.0, "raise": 0.25, "raiseCallIP": 0.25, "raiseCallOP": 0.25}, {"id": 1193207, "card1": "A", "card2": "A", "card3": "T", "card4": "2", "doubleSuited": false, "goodSuit": false, "fold": 0.0, "call": 0.0, "raise": 0.5, "raiseCallIP": 0.5, "raiseCallOP": 0.5}, {"id": 1193210, "card1": "A", "card2": "A", "card3": "T", "card4": "2", "doubleSuited": false, "goodSuit": true, "fold": 0.0, "call": 0.0, "raise": 0.5, "raiseCallIP": 0.5, "raiseCallOP": 0.5}, {"id": 1193266, "card1": "A", "card2": "A", "card3": "T", "card4": "3", "doubleSuited": false, "goodSuit": false, "fold": 0.0, "call": 0.0, "raise": 0.5, "raiseCallIP": 0.5, "raiseCallOP": 0.5}, {"id": 1193269, "card1": "A", "card2": "A", "card3": "T", "card4": "3", "doubleSuited": false, "goodSuit": true, "fold": 0.0, "call": 0.0, "raise": 0.5, "raiseCallIP": 0.5, "raiseCallOP": 0.5}, {"id": 1193494, "card1": "A", "card2": "A", "card3": "T", "card4": "8", "doubleSuited": false, "goodSuit": false, "fold": 0.0, "call": 0.0, "raise": 0.5, "raiseCallIP": 0.5, "raiseCallOP": 0.5}, {"id": 1193497, "card1": "A", "card2": "A", "card3": "T", "card4": "8", "doubleSuited": false, "goodSuit": true, "fold": 0.0, "call": 0.0, "raise": 0.5, "raiseCallIP": 0.5, "raiseCallOP": 0.5}, {"id": 1193507, "card1": "A", "card2": "A", "card3": "T", "card4": "9", "doubleSuited": false, "goodSuit": false, "fold": 0.0, "call": 0.0, "raise": 0.5, "raiseCallIP": 0.5, "raiseCallOP": 0.5}, {"id": 1193510, "card1": "A", "card2": "A", "card3": "T", "card4": "9", "doubleSuited": false, "goodSuit": true, "fold": 0.0, "call": 0.0, "raise": 0.5, "raiseCallIP": 0.5, "raiseCallOP": 0.5}, {"id": 1193519, "card1": "A", "card2": "A", "card3": "T", "card4": "6", "doubleSuited": false, "goodSuit": false, "fold": 0.0, "call": 0.0, "raise": 0.5, "raiseCallIP": 0.5, "raiseCallOP": 0.5}, {"id": 1193523, "card1": "A", "card2": "A", "card3": "T", "card4": "6", "doubleSuited": false, "goodSuit": true, "fold": 0.0, "call": 0.0, "raise": 0.5, "raiseCallIP": 0.5, "raiseCallOP": 0.5}, {"id": 1193538, "card1": "A", "card2": "A", "card3": "T", "card4": "7", "doubleSuited": false, "goodSuit": false, "fold": 0.0, "call": 0.0, "raise": 0.5, "raiseCallIP": 0.5, "raiseCallOP": 0.5}, {"id": 1193541, "card1": "A", "card2": "A", "card3": "T", "card4": "7", "doubleSuited": false, "goodSuit": true, "fold": 0.0, "call": 0.0, "raise": 0.5, "raiseCallIP": 0.5, "raiseCallOP": 0.5}, {"id": 1193549, "card1": "A", "card2": "A", "card3": "T", "card4": "4", "doubleSuited": false, "goodSuit": false, "fold": 0.0, "call": 0.0, "raise": 0.5, "raiseCallIP": 0.5, "raiseCallOP": 0.5}, {"id": 1193552, "card1": "A", "card2": "A", "card3": "T", "card4": "4", "doubleSuited": false, "goodSuit": true, "fold": 0.0, "call": 0.0, "raise": 0.5, "raiseCallIP": 0.5, "raiseCallOP": 0.5}, {"id": 1193561, "card1": "A", "card2": "A", "card3": "T", "card4": "5", "doubleSuited": false, "goodSuit": false, "fold": 0.0, "call": 0.0, "raise": 0.5, "raiseCallIP": 0.5, "raiseCallOP": 0.5}, {"id": 1193565, "card1": "A", "card2": "A", "card3": "T", "card4": "5", "doubleSuited": false, "goodSuit": true, "fold": 0.0, "call": 0.0, "raise": 0.5, "raiseCallIP": 0.5, "raiseCallOP": 0.5}, {"id": 1193672, "card1": "A", "card2": "A", "card3": "T", "card4": "T", "doubleSuited": false, "goodSuit": true, "fold": 0.0, "call": 0.0, "raise": 0.25, "raiseCallIP": 0.25, "raiseCallOP": 0.25}]