[{"id": 725698, "card1": "T", "card2": "T", "card3": "3", "card4": "3", "doubleSuited": false, "goodSuit": true, "fold": 0.25}, {"id": 725788, "card1": "T", "card2": "T", "card3": "4", "card4": "3", "doubleSuited": false, "goodSuit": false, "fold": 0.5}, {"id": 725789, "card1": "T", "card2": "T", "card3": "4", "card4": "3", "doubleSuited": false, "goodSuit": true, "fold": 0.5}, {"id": 725796, "card1": "T", "card2": "T", "card3": "4", "card4": "2", "doubleSuited": false, "goodSuit": false, "fold": 0.5}, {"id": 725797, "card1": "T", "card2": "T", "card3": "4", "card4": "2", "doubleSuited": false, "goodSuit": true, "fold": 0.5}, {"id": 725851, "card1": "T", "card2": "T", "card3": "2", "card4": "2", "doubleSuited": false, "goodSuit": true, "fold": 0.25}, {"id": 725917, "card1": "T", "card2": "T", "card3": "3", "card4": "2", "doubleSuited": false, "goodSuit": false, "fold": 0.5}, {"id": 725919, "card1": "T", "card2": "T", "card3": "3", "card4": "2", "doubleSuited": false, "goodSuit": true, "fold": 0.5}, {"id": 726010, "card1": "T", "card2": "T", "card3": "5", "card4": "5", "doubleSuited": false, "goodSuit": true, "fold": 0.25}, {"id": 726064, "card1": "T", "card2": "T", "card3": "6", "card4": "5", "doubleSuited": false, "goodSuit": false, "fold": 0.5}, {"id": 726065, "card1": "T", "card2": "T", "card3": "6", "card4": "5", "doubleSuited": false, "goodSuit": true, "fold": 0.5}, {"id": 726073, "card1": "T", "card2": "T", "card3": "6", "card4": "4", "doubleSuited": false, "goodSuit": false, "fold": 0.5}, {"id": 726075, "card1": "T", "card2": "T", "card3": "6", "card4": "4", "doubleSuited": false, "goodSuit": true, "fold": 0.5}, {"id": 726092, "card1": "T", "card2": "T", "card3": "6", "card4": "3", "doubleSuited": false, "goodSuit": false, "fold": 0.5}, {"id": 726094, "card1": "T", "card2": "T", "card3": "6", "card4": "3", "doubleSuited": false, "goodSuit": true, "fold": 0.5}, {"id": 726102, "card1": "T", "card2": "T", "card3": "6", "card4": "2", "doubleSuited": false, "goodSuit": false, "fold": 0.5}, {"id": 726105, "card1": "T", "card2": "T", "card3": "6", "card4": "2", "doubleSuited": false, "goodSuit": true, "fold": 0.5}, {"id": 726167, "card1": "T", "card2": "T", "card3": "4", "card4": "4", "doubleSuited": false, "goodSuit": true, "fold": 0.25}, {"id": 726283, "card1": "T", "card2": "T", "card3": "5", "card4": "4", "doubleSuited": false, "goodSuit": false, "fold": 0.5}, {"id": 726285, "card1": "T", "card2": "T", "card3": "5", "card4": "4", "doubleSuited": false, "goodSuit": true, "fold": 0.5}, {"id": 726301, "card1": "T", "card2": "T", "card3": "5", "card4": "3", "doubleSuited": false, "goodSuit": false, "fold": 0.5}, {"id": 726306, "card1": "T", "card2": "T", "card3": "5", "card4": "3", "doubleSuited": false, "goodSuit": true, "fold": 0.5}, {"id": 726328, "card1": "T", "card2": "T", "card3": "5", "card4": "2", "doubleSuited": false, "goodSuit": false, "fold": 0.5}, {"id": 726331, "card1": "T", "card2": "T", "card3": "5", "card4": "2", "doubleSuited": false, "goodSuit": true, "fold": 0.5}, {"id": 726391, "card1": "T", "card2": "T", "card3": "7", "card4": "7", "doubleSuited": false, "goodSuit": true, "fold": 0.25}, {"id": 726454, "card1": "T", "card2": "T", "card3": "8", "card4": "7", "doubleSuited": false, "goodSuit": false, "fold": 0.5}, {"id": 726457, "card1": "T", "card2": "T", "card3": "8", "card4": "7", "doubleSuited": false, "goodSuit": true, "fold": 0.5}, {"id": 726462, "card1": "T", "card2": "T", "card3": "8", "card4": "6", "doubleSuited": false, "goodSuit": false, "fold": 0.5}, {"id": 726465, "card1": "T", "card2": "T", "card3": "8", "card4": "6", "doubleSuited": false, "goodSuit": true, "fold": 0.5}, {"id": 726471, "card1": "T", "card2": "T", "card3": "8", "card4": "5", "doubleSuited": false, "goodSuit": false, "fold": 0.5}, {"id": 726472, "card1": "T", "card2": "T", "card3": "8", "card4": "5", "doubleSuited": false, "goodSuit": true, "fold": 0.5}, {"id": 726479, "card1": "T", "card2": "T", "card3": "8", "card4": "4", "doubleSuited": false, "goodSuit": false, "fold": 0.5}, {"id": 726481, "card1": "T", "card2": "T", "card3": "8", "card4": "4", "doubleSuited": false, "goodSuit": true, "fold": 0.5}, {"id": 726488, "card1": "T", "card2": "T", "card3": "8", "card4": "3", "doubleSuited": false, "goodSuit": false, "fold": 0.5}, {"id": 726492, "card1": "T", "card2": "T", "card3": "8", "card4": "3", "doubleSuited": false, "goodSuit": true, "fold": 0.5}, {"id": 726499, "card1": "T", "card2": "T", "card3": "8", "card4": "2", "doubleSuited": false, "goodSuit": false, "fold": 0.5}, {"id": 726501, "card1": "T", "card2": "T", "card3": "8", "card4": "2", "doubleSuited": false, "goodSuit": true, "fold": 0.5}, {"id": 726521, "card1": "T", "card2": "T", "card3": "6", "card4": "6", "doubleSuited": false, "goodSuit": true, "fold": 0.25}, {"id": 726572, "card1": "T", "card2": "T", "card3": "7", "card4": "6", "doubleSuited": false, "goodSuit": false, "fold": 0.5}, {"id": 726574, "card1": "T", "card2": "T", "card3": "7", "card4": "6", "doubleSuited": false, "goodSuit": true, "fold": 0.5}, {"id": 726590, "card1": "T", "card2": "T", "card3": "7", "card4": "5", "doubleSuited": false, "goodSuit": false, "fold": 0.5}, {"id": 726591, "card1": "T", "card2": "T", "card3": "7", "card4": "5", "doubleSuited": false, "goodSuit": true, "fold": 0.5}, {"id": 726610, "card1": "T", "card2": "T", "card3": "7", "card4": "4", "doubleSuited": false, "goodSuit": false, "fold": 0.5}, {"id": 726612, "card1": "T", "card2": "T", "card3": "7", "card4": "4", "doubleSuited": false, "goodSuit": true, "fold": 0.5}, {"id": 726631, "card1": "T", "card2": "T", "card3": "7", "card4": "3", "doubleSuited": false, "goodSuit": false, "fold": 0.5}, {"id": 726636, "card1": "T", "card2": "T", "card3": "7", "card4": "3", "doubleSuited": false, "goodSuit": true, "fold": 0.5}, {"id": 726652, "card1": "T", "card2": "T", "card3": "7", "card4": "2", "doubleSuited": false, "goodSuit": false, "fold": 0.5}, {"id": 726653, "card1": "T", "card2": "T", "card3": "7", "card4": "2", "doubleSuited": false, "goodSuit": true, "fold": 0.5}, {"id": 726741, "card1": "T", "card2": "T", "card3": "8", "card4": "8", "doubleSuited": false, "goodSuit": true, "fold": 0.248837, "call": 0.025358}, {"id": 726747, "card1": "T", "card2": "T", "card3": "9", "card4": "8", "doubleSuited": false, "goodSuit": false, "fold": 0.5}, {"id": 726749, "card1": "T", "card2": "T", "card3": "9", "card4": "8", "doubleSuited": false, "goodSuit": true, "fold": 0.5}, {"id": 726754, "card1": "T", "card2": "T", "card3": "9", "card4": "7", "doubleSuited": false, "goodSuit": false, "fold": 0.5}, {"id": 726757, "card1": "T", "card2": "T", "card3": "9", "card4": "7", "doubleSuited": false, "goodSuit": true, "fold": 0.5}, {"id": 726762, "card1": "T", "card2": "T", "card3": "9", "card4": "6", "doubleSuited": false, "goodSuit": false, "fold": 0.5}, {"id": 726765, "card1": "T", "card2": "T", "card3": "9", "card4": "6", "doubleSuited": false, "goodSuit": true, "fold": 0.5}, {"id": 726771, "card1": "T", "card2": "T", "card3": "9", "card4": "5", "doubleSuited": false, "goodSuit": false, "fold": 0.5}, {"id": 726773, "card1": "T", "card2": "T", "card3": "9", "card4": "5", "doubleSuited": false, "goodSuit": true, "fold": 0.5}, {"id": 726781, "card1": "T", "card2": "T", "card3": "9", "card4": "4", "doubleSuited": false, "goodSuit": false, "fold": 0.5}, {"id": 726782, "card1": "T", "card2": "T", "card3": "9", "card4": "4", "doubleSuited": false, "goodSuit": true, "fold": 0.5}, {"id": 726790, "card1": "T", "card2": "T", "card3": "9", "card4": "3", "doubleSuited": false, "goodSuit": false, "fold": 0.5}, {"id": 726792, "card1": "T", "card2": "T", "card3": "9", "card4": "3", "doubleSuited": false, "goodSuit": true, "fold": 0.5}, {"id": 726801, "card1": "T", "card2": "T", "card3": "9", "card4": "2", "doubleSuited": false, "goodSuit": false, "fold": 0.5}, {"id": 726804, "card1": "T", "card2": "T", "card3": "9", "card4": "2", "doubleSuited": false, "goodSuit": true, "fold": 0.5}, {"id": 727266, "card1": "T", "card2": "T", "card3": "A", "card4": "T", "doubleSuited": false, "goodSuit": true, "fold": 0.166667}, {"id": 727374, "card1": "T", "card2": "T", "card3": "A", "card4": "8", "doubleSuited": false, "goodSuit": false, "fold": 0.5}, {"id": 727386, "card1": "T", "card2": "T", "card3": "A", "card4": "7", "doubleSuited": false, "goodSuit": false, "fold": 0.5}, {"id": 727390, "card1": "T", "card2": "T", "card3": "A", "card4": "7", "doubleSuited": false, "goodSuit": true, "fold": 0.5}, {"id": 727397, "card1": "T", "card2": "T", "card3": "A", "card4": "6", "doubleSuited": false, "goodSuit": false, "fold": 0.5}, {"id": 727398, "card1": "T", "card2": "T", "card3": "A", "card4": "6", "doubleSuited": false, "goodSuit": true, "fold": 0.5}, {"id": 727404, "card1": "T", "card2": "T", "card3": "A", "card4": "5", "doubleSuited": false, "goodSuit": false, "fold": 0.5}, {"id": 727407, "card1": "T", "card2": "T", "card3": "A", "card4": "5", "doubleSuited": false, "goodSuit": true, "fold": 0.5}, {"id": 727414, "card1": "T", "card2": "T", "card3": "A", "card4": "4", "doubleSuited": false, "goodSuit": false, "fold": 0.5}, {"id": 727415, "card1": "T", "card2": "T", "card3": "A", "card4": "4", "doubleSuited": false, "goodSuit": true, "fold": 0.5}, {"id": 727422, "card1": "T", "card2": "T", "card3": "A", "card4": "3", "doubleSuited": false, "goodSuit": false, "fold": 0.5}, {"id": 727424, "card1": "T", "card2": "T", "card3": "A", "card4": "3", "doubleSuited": false, "goodSuit": true, "fold": 0.5}, {"id": 727429, "card1": "T", "card2": "T", "card3": "A", "card4": "2", "doubleSuited": false, "goodSuit": false, "fold": 0.5}, {"id": 727432, "card1": "T", "card2": "T", "card3": "A", "card4": "2", "doubleSuited": false, "goodSuit": true, "fold": 0.5}, {"id": 727443, "card1": "T", "card2": "T", "card3": "A", "card4": "9", "doubleSuited": false, "goodSuit": false, "fold": 0.5}, {"id": 727939, "card1": "T", "card2": "T", "card3": "J", "card4": "9", "doubleSuited": false, "goodSuit": false, "fold": 0.5}, {"id": 727941, "card1": "T", "card2": "T", "card3": "J", "card4": "9", "doubleSuited": false, "goodSuit": true, "fold": 0.5}, {"id": 727948, "card1": "T", "card2": "T", "card3": "J", "card4": "8", "doubleSuited": false, "goodSuit": false, "fold": 0.5}, {"id": 727949, "card1": "T", "card2": "T", "card3": "J", "card4": "8", "doubleSuited": false, "goodSuit": true, "fold": 0.5}, {"id": 727956, "card1": "T", "card2": "T", "card3": "J", "card4": "7", "doubleSuited": false, "goodSuit": false, "fold": 0.5}, {"id": 727958, "card1": "T", "card2": "T", "card3": "J", "card4": "7", "doubleSuited": false, "goodSuit": true, "fold": 0.5}, {"id": 727965, "card1": "T", "card2": "T", "card3": "J", "card4": "6", "doubleSuited": false, "goodSuit": false, "fold": 0.5}, {"id": 727968, "card1": "T", "card2": "T", "card3": "J", "card4": "6", "doubleSuited": false, "goodSuit": true, "fold": 0.5}, {"id": 727976, "card1": "T", "card2": "T", "card3": "J", "card4": "5", "doubleSuited": false, "goodSuit": false, "fold": 0.5}, {"id": 727979, "card1": "T", "card2": "T", "card3": "J", "card4": "5", "doubleSuited": false, "goodSuit": true, "fold": 0.5}, {"id": 727989, "card1": "T", "card2": "T", "card3": "J", "card4": "4", "doubleSuited": false, "goodSuit": false, "fold": 0.5}, {"id": 727992, "card1": "T", "card2": "T", "card3": "J", "card4": "4", "doubleSuited": false, "goodSuit": true, "fold": 0.5}, {"id": 728000, "card1": "T", "card2": "T", "card3": "J", "card4": "3", "doubleSuited": false, "goodSuit": false, "fold": 0.5}, {"id": 728003, "card1": "T", "card2": "T", "card3": "J", "card4": "3", "doubleSuited": false, "goodSuit": true, "fold": 0.5}, {"id": 728011, "card1": "T", "card2": "T", "card3": "J", "card4": "2", "doubleSuited": false, "goodSuit": false, "fold": 0.5}, {"id": 728015, "card1": "T", "card2": "T", "card3": "J", "card4": "2", "doubleSuited": false, "goodSuit": true, "fold": 0.5}, {"id": 728044, "card1": "T", "card2": "T", "card3": "K", "card4": "Q", "doubleSuited": false, "goodSuit": false, "fold": 0.5}, {"id": 728045, "card1": "T", "card2": "T", "card3": "K", "card4": "Q", "doubleSuited": false, "goodSuit": true, "fold": 0.5}, {"id": 728083, "card1": "T", "card2": "T", "card3": "K", "card4": "T", "doubleSuited": false, "goodSuit": true, "fold": 0.166667}, {"id": 728106, "card1": "T", "card2": "T", "card3": "K", "card4": "2", "doubleSuited": false, "goodSuit": false, "fold": 0.5}, {"id": 728110, "card1": "T", "card2": "T", "card3": "K", "card4": "2", "doubleSuited": false, "goodSuit": true, "fold": 0.5}, {"id": 728136, "card1": "T", "card2": "T", "card3": "K", "card4": "9", "doubleSuited": false, "goodSuit": false, "fold": 0.5}, {"id": 728140, "card1": "T", "card2": "T", "card3": "K", "card4": "9", "doubleSuited": false, "goodSuit": true, "fold": 0.497198, "raise": 0.002802, "raiseCallIP": 0.002802, "raiseCallOP": 0.002802}, {"id": 728145, "card1": "T", "card2": "T", "card3": "K", "card4": "8", "doubleSuited": false, "goodSuit": false, "fold": 0.5}, {"id": 728148, "card1": "T", "card2": "T", "card3": "K", "card4": "8", "doubleSuited": false, "goodSuit": true, "fold": 0.5}, {"id": 728152, "card1": "T", "card2": "T", "card3": "K", "card4": "7", "doubleSuited": false, "goodSuit": false, "fold": 0.5}, {"id": 728157, "card1": "T", "card2": "T", "card3": "K", "card4": "7", "doubleSuited": false, "goodSuit": true, "fold": 0.5}, {"id": 728164, "card1": "T", "card2": "T", "card3": "K", "card4": "6", "doubleSuited": false, "goodSuit": false, "fold": 0.5}, {"id": 728168, "card1": "T", "card2": "T", "card3": "K", "card4": "6", "doubleSuited": false, "goodSuit": true, "fold": 0.5}, {"id": 728171, "card1": "T", "card2": "T", "card3": "K", "card4": "5", "doubleSuited": false, "goodSuit": false, "fold": 0.5}, {"id": 728174, "card1": "T", "card2": "T", "card3": "K", "card4": "5", "doubleSuited": false, "goodSuit": true, "fold": 0.5}, {"id": 728183, "card1": "T", "card2": "T", "card3": "J", "card4": "T", "doubleSuited": false, "goodSuit": true, "fold": 0.166667}, {"id": 728190, "card1": "T", "card2": "T", "card3": "K", "card4": "4", "doubleSuited": false, "goodSuit": false, "fold": 0.5}, {"id": 728193, "card1": "T", "card2": "T", "card3": "K", "card4": "4", "doubleSuited": false, "goodSuit": true, "fold": 0.5}, {"id": 728200, "card1": "T", "card2": "T", "card3": "K", "card4": "3", "doubleSuited": false, "goodSuit": false, "fold": 0.5}, {"id": 728204, "card1": "T", "card2": "T", "card3": "K", "card4": "3", "doubleSuited": false, "goodSuit": true, "fold": 0.5}, {"id": 728213, "card1": "T", "card2": "T", "card3": "K", "card4": "J", "doubleSuited": false, "goodSuit": false, "fold": 0.5}, {"id": 728216, "card1": "T", "card2": "T", "card3": "K", "card4": "J", "doubleSuited": false, "goodSuit": true, "fold": 0.165705, "call": 0.020983, "raise": 0.333333, "raiseCallIP": 0.333333, "raiseCallOP": 0.333333}, {"id": 729033, "card1": "T", "card2": "T", "card3": "Q", "card4": "T", "doubleSuited": false, "goodSuit": true, "fold": 0.166667}, {"id": 729252, "card1": "T", "card2": "T", "card3": "Q", "card4": "8", "doubleSuited": false, "goodSuit": false, "fold": 0.5}, {"id": 729255, "card1": "T", "card2": "T", "card3": "Q", "card4": "8", "doubleSuited": false, "goodSuit": true, "fold": 0.5}, {"id": 729262, "card1": "T", "card2": "T", "card3": "Q", "card4": "7", "doubleSuited": false, "goodSuit": false, "fold": 0.5}, {"id": 729265, "card1": "T", "card2": "T", "card3": "Q", "card4": "7", "doubleSuited": false, "goodSuit": true, "fold": 0.5}, {"id": 729275, "card1": "T", "card2": "T", "card3": "Q", "card4": "6", "doubleSuited": false, "goodSuit": false, "fold": 0.5}, {"id": 729278, "card1": "T", "card2": "T", "card3": "Q", "card4": "6", "doubleSuited": false, "goodSuit": true, "fold": 0.5}, {"id": 729287, "card1": "T", "card2": "T", "card3": "Q", "card4": "5", "doubleSuited": false, "goodSuit": false, "fold": 0.5}, {"id": 729291, "card1": "T", "card2": "T", "card3": "Q", "card4": "5", "doubleSuited": false, "goodSuit": true, "fold": 0.5}, {"id": 729300, "card1": "T", "card2": "T", "card3": "Q", "card4": "4", "doubleSuited": false, "goodSuit": false, "fold": 0.5}, {"id": 729303, "card1": "T", "card2": "T", "card3": "Q", "card4": "4", "doubleSuited": false, "goodSuit": true, "fold": 0.5}, {"id": 729324, "card1": "T", "card2": "T", "card3": "Q", "card4": "3", "doubleSuited": false, "goodSuit": false, "fold": 0.5}, {"id": 729327, "card1": "T", "card2": "T", "card3": "Q", "card4": "3", "doubleSuited": false, "goodSuit": true, "fold": 0.5}, {"id": 729336, "card1": "T", "card2": "T", "card3": "Q", "card4": "2", "doubleSuited": false, "goodSuit": false, "fold": 0.5}, {"id": 729339, "card1": "T", "card2": "T", "card3": "Q", "card4": "2", "doubleSuited": false, "goodSuit": true, "fold": 0.5}, {"id": 729479, "card1": "T", "card2": "T", "card3": "Q", "card4": "9", "doubleSuited": false, "goodSuit": false, "fold": 0.5}, {"id": 729482, "card1": "T", "card2": "T", "card3": "Q", "card4": "9", "doubleSuited": false, "goodSuit": true, "fold": 0.5}, {"id": 729577, "card1": "T", "card2": "T", "card3": "Q", "card4": "J", "doubleSuited": false, "goodSuit": false, "fold": 0.5}, {"id": 729581, "card1": "T", "card2": "T", "card3": "Q", "card4": "J", "doubleSuited": false, "goodSuit": true, "fold": 0.5}, {"id": 729603, "card1": "T", "card2": "T", "card3": "T", "card4": "9", "doubleSuited": false, "goodSuit": true, "fold": 0.166667}, {"id": 729609, "card1": "T", "card2": "T", "card3": "T", "card4": "8", "doubleSuited": false, "goodSuit": true, "fold": 0.166667}, {"id": 729615, "card1": "T", "card2": "T", "card3": "T", "card4": "7", "doubleSuited": false, "goodSuit": true, "fold": 0.166667}, {"id": 729620, "card1": "T", "card2": "T", "card3": "T", "card4": "6", "doubleSuited": false, "goodSuit": true, "fold": 0.166667}, {"id": 729627, "card1": "T", "card2": "T", "card3": "T", "card4": "5", "doubleSuited": false, "goodSuit": true, "fold": 0.166667}, {"id": 729633, "card1": "T", "card2": "T", "card3": "T", "card4": "4", "doubleSuited": false, "goodSuit": true, "fold": 0.166667}, {"id": 729923, "card1": "T", "card2": "T", "card3": "T", "card4": "3", "doubleSuited": false, "goodSuit": true, "fold": 0.166667}, {"id": 729928, "card1": "T", "card2": "T", "card3": "T", "card4": "2", "doubleSuited": false, "goodSuit": true, "fold": 0.166667}, {"id": 746595, "card1": "T", "card2": "T", "card3": "9", "card4": "9", "doubleSuited": false, "goodSuit": true, "raise": 0.25, "raiseCallIP": 0.25, "raiseCallOP": 0.25}, {"id": 747152, "card1": "T", "card2": "T", "card3": "A", "card4": "K", "doubleSuited": false, "goodSuit": false, "raise": 0.5, "raiseCallIP": 0.5, "raiseCallOP": 0.5}, {"id": 747153, "card1": "T", "card2": "T", "card3": "A", "card4": "K", "doubleSuited": false, "goodSuit": true, "raise": 0.5, "raiseCallIP": 0.5, "raiseCallOP": 0.5}, {"id": 747167, "card1": "T", "card2": "T", "card3": "A", "card4": "J", "doubleSuited": false, "goodSuit": false, "raise": 0.5, "raiseCallIP": 0.5, "raiseCallOP": 0.5}, {"id": 747169, "card1": "T", "card2": "T", "card3": "A", "card4": "J", "doubleSuited": false, "goodSuit": true, "raise": 0.5, "raiseCallIP": 0.5, "raiseCallOP": 0.5}, {"id": 747205, "card1": "T", "card2": "T", "card3": "A", "card4": "Q", "doubleSuited": false, "goodSuit": false, "raise": 0.5, "raiseCallIP": 0.5, "raiseCallOP": 0.5}, {"id": 747207, "card1": "T", "card2": "T", "card3": "A", "card4": "Q", "doubleSuited": false, "goodSuit": true, "raise": 0.5, "raiseCallIP": 0.5, "raiseCallOP": 0.5}, {"id": 747378, "card1": "T", "card2": "T", "card3": "A", "card4": "8", "doubleSuited": false, "goodSuit": true, "raise": 0.5, "raiseCallIP": 0.5, "raiseCallOP": 0.5}, {"id": 747415, "card1": "T", "card2": "T", "card3": "A", "card4": "9", "doubleSuited": false, "goodSuit": true, "raise": 0.5, "raiseCallIP": 0.5, "raiseCallOP": 0.5}]