[{"id": 869979, "card1": "K", "card2": "K", "card3": "7", "card4": "2", "doubleSuited": false, "goodSuit": false, "fold": 0.5}, {"id": 870009, "card1": "K", "card2": "K", "card3": "7", "card4": "3", "doubleSuited": false, "goodSuit": false, "fold": 0.25, "call": 0.25}, {"id": 870317, "card1": "K", "card2": "K", "card3": "6", "card4": "2", "doubleSuited": false, "goodSuit": false, "fold": 0.25, "call": 0.25}, {"id": 870534, "card1": "K", "card2": "K", "card3": "9", "card4": "4", "doubleSuited": false, "goodSuit": false, "fold": 0.200241, "call": 0.299759}, {"id": 870562, "card1": "K", "card2": "K", "card3": "9", "card4": "3", "doubleSuited": false, "goodSuit": false, "fold": 0.143452, "call": 0.356548}, {"id": 871012, "card1": "K", "card2": "K", "card3": "8", "card4": "3", "doubleSuited": false, "goodSuit": false, "fold": 0.5}, {"id": 871040, "card1": "K", "card2": "K", "card3": "8", "card4": "2", "doubleSuited": false, "goodSuit": false, "fold": 0.5}, {"id": 871096, "card1": "K", "card2": "K", "card3": "8", "card4": "4", "doubleSuited": false, "goodSuit": false, "fold": 0.25, "call": 0.25}, {"id": 873894, "card1": "K", "card2": "K", "card3": "A", "card4": "K", "doubleSuited": false, "goodSuit": true, "fold": 0.166667}, {"id": 874913, "card1": "K", "card2": "K", "card3": "K", "card4": "2", "doubleSuited": false, "goodSuit": true, "fold": 0.166667}, {"id": 874924, "card1": "K", "card2": "K", "card3": "K", "card4": "6", "doubleSuited": false, "goodSuit": true, "fold": 0.166667}, {"id": 874935, "card1": "K", "card2": "K", "card3": "K", "card4": "5", "doubleSuited": false, "goodSuit": true, "fold": 0.166667}, {"id": 874944, "card1": "K", "card2": "K", "card3": "K", "card4": "4", "doubleSuited": false, "goodSuit": true, "fold": 0.166667}, {"id": 874956, "card1": "K", "card2": "K", "card3": "K", "card4": "3", "doubleSuited": false, "goodSuit": true, "fold": 0.166667}, {"id": 874966, "card1": "K", "card2": "K", "card3": "K", "card4": "9", "doubleSuited": false, "goodSuit": true, "fold": 0.166667}, {"id": 874978, "card1": "K", "card2": "K", "card3": "K", "card4": "8", "doubleSuited": false, "goodSuit": true, "fold": 0.166667}, {"id": 874990, "card1": "K", "card2": "K", "card3": "K", "card4": "7", "doubleSuited": false, "goodSuit": true, "fold": 0.166667}, {"id": 875000, "card1": "K", "card2": "K", "card3": "K", "card4": "J", "doubleSuited": false, "goodSuit": true, "fold": 0.166667}, {"id": 875169, "card1": "K", "card2": "K", "card3": "K", "card4": "Q", "doubleSuited": false, "goodSuit": true, "fold": 0.166667}, {"id": 875180, "card1": "K", "card2": "K", "card3": "K", "card4": "T", "doubleSuited": false, "goodSuit": true, "fold": 0.166667}, {"id": 884579, "card1": "K", "card2": "K", "card3": "6", "card4": "6", "doubleSuited": false, "goodSuit": true, "call": 0.25}, {"id": 884806, "card1": "K", "card2": "K", "card3": "7", "card4": "2", "doubleSuited": false, "goodSuit": true, "call": 0.5}, {"id": 884826, "card1": "K", "card2": "K", "card3": "7", "card4": "6", "doubleSuited": false, "goodSuit": false, "call": 0.5}, {"id": 884831, "card1": "K", "card2": "K", "card3": "7", "card4": "6", "doubleSuited": false, "goodSuit": true, "call": 0.5}, {"id": 884859, "card1": "K", "card2": "K", "card3": "7", "card4": "5", "doubleSuited": false, "goodSuit": false, "call": 0.5}, {"id": 884864, "card1": "K", "card2": "K", "card3": "7", "card4": "5", "doubleSuited": false, "goodSuit": true, "call": 0.5}, {"id": 884890, "card1": "K", "card2": "K", "card3": "7", "card4": "4", "doubleSuited": false, "goodSuit": false, "call": 0.5}, {"id": 884896, "card1": "K", "card2": "K", "card3": "7", "card4": "4", "doubleSuited": false, "goodSuit": true, "call": 0.5}, {"id": 884923, "card1": "K", "card2": "K", "card3": "7", "card4": "3", "doubleSuited": false, "goodSuit": true, "call": 0.5}, {"id": 885006, "card1": "K", "card2": "K", "card3": "5", "card4": "5", "doubleSuited": false, "goodSuit": true, "call": 0.25}, {"id": 885230, "card1": "K", "card2": "K", "card3": "6", "card4": "5", "doubleSuited": false, "goodSuit": false, "call": 0.5}, {"id": 885236, "card1": "K", "card2": "K", "card3": "6", "card4": "5", "doubleSuited": false, "goodSuit": true, "call": 0.5}, {"id": 885259, "card1": "K", "card2": "K", "card3": "6", "card4": "4", "doubleSuited": false, "goodSuit": false, "call": 0.5}, {"id": 885265, "card1": "K", "card2": "K", "card3": "6", "card4": "4", "doubleSuited": false, "goodSuit": true, "call": 0.5}, {"id": 885285, "card1": "K", "card2": "K", "card3": "6", "card4": "3", "doubleSuited": false, "goodSuit": false, "call": 0.5}, {"id": 885291, "card1": "K", "card2": "K", "card3": "6", "card4": "3", "doubleSuited": false, "goodSuit": true, "call": 0.5}, {"id": 885310, "card1": "K", "card2": "K", "card3": "6", "card4": "2", "doubleSuited": false, "goodSuit": true, "call": 0.5}, {"id": 885349, "card1": "K", "card2": "K", "card3": "8", "card4": "8", "doubleSuited": false, "goodSuit": true, "call": 0.25}, {"id": 885556, "card1": "K", "card2": "K", "card3": "9", "card4": "4", "doubleSuited": false, "goodSuit": true, "call": 0.5}, {"id": 885579, "card1": "K", "card2": "K", "card3": "9", "card4": "3", "doubleSuited": false, "goodSuit": true, "call": 0.5}, {"id": 885590, "card1": "K", "card2": "K", "card3": "9", "card4": "2", "doubleSuited": false, "goodSuit": false, "call": 0.5}, {"id": 885598, "card1": "K", "card2": "K", "card3": "9", "card4": "2", "doubleSuited": false, "goodSuit": true, "call": 0.5}, {"id": 885612, "card1": "K", "card2": "K", "card3": "9", "card4": "8", "doubleSuited": false, "goodSuit": false, "call": 0.5}, {"id": 885617, "card1": "K", "card2": "K", "card3": "9", "card4": "8", "doubleSuited": false, "goodSuit": true, "call": 0.5}, {"id": 885631, "card1": "K", "card2": "K", "card3": "9", "card4": "7", "doubleSuited": false, "goodSuit": false, "call": 0.5}, {"id": 885635, "card1": "K", "card2": "K", "card3": "9", "card4": "7", "doubleSuited": false, "goodSuit": true, "call": 0.5}, {"id": 885649, "card1": "K", "card2": "K", "card3": "9", "card4": "6", "doubleSuited": false, "goodSuit": false, "call": 0.5}, {"id": 885652, "card1": "K", "card2": "K", "card3": "9", "card4": "6", "doubleSuited": false, "goodSuit": true, "call": 0.5}, {"id": 885662, "card1": "K", "card2": "K", "card3": "9", "card4": "5", "doubleSuited": false, "goodSuit": false, "call": 0.5}, {"id": 885668, "card1": "K", "card2": "K", "card3": "9", "card4": "5", "doubleSuited": false, "goodSuit": true, "call": 0.5}, {"id": 885698, "card1": "K", "card2": "K", "card3": "7", "card4": "7", "doubleSuited": false, "goodSuit": true, "call": 0.25}, {"id": 885838, "card1": "K", "card2": "K", "card3": "8", "card4": "3", "doubleSuited": false, "goodSuit": true, "call": 0.5}, {"id": 885859, "card1": "K", "card2": "K", "card3": "8", "card4": "2", "doubleSuited": false, "goodSuit": true, "call": 0.5}, {"id": 885882, "card1": "K", "card2": "K", "card3": "8", "card4": "7", "doubleSuited": false, "goodSuit": false, "call": 0.5}, {"id": 885886, "card1": "K", "card2": "K", "card3": "8", "card4": "7", "doubleSuited": false, "goodSuit": true, "call": 0.5}, {"id": 885922, "card1": "K", "card2": "K", "card3": "8", "card4": "6", "doubleSuited": false, "goodSuit": false, "call": 0.5}, {"id": 885926, "card1": "K", "card2": "K", "card3": "8", "card4": "6", "doubleSuited": false, "goodSuit": true, "call": 0.5}, {"id": 885949, "card1": "K", "card2": "K", "card3": "8", "card4": "5", "doubleSuited": false, "goodSuit": false, "call": 0.5}, {"id": 885955, "card1": "K", "card2": "K", "card3": "8", "card4": "5", "doubleSuited": false, "goodSuit": true, "call": 0.5}, {"id": 885976, "card1": "K", "card2": "K", "card3": "8", "card4": "4", "doubleSuited": false, "goodSuit": true, "call": 0.5}, {"id": 886143, "card1": "K", "card2": "K", "card3": "9", "card4": "9", "doubleSuited": false, "goodSuit": true, "call": 0.25}, {"id": 887302, "card1": "K", "card2": "K", "card3": "A", "card4": "4", "doubleSuited": false, "goodSuit": false, "call": 0.044912, "raise": 0.455088, "raiseFoldIP": 0.455088, "raiseFoldOP": 0.455088}, {"id": 887307, "card1": "K", "card2": "K", "card3": "A", "card4": "4", "doubleSuited": false, "goodSuit": true, "call": 0.333333, "raise": 0.166667, "raiseFoldIP": 0.166667, "raiseFoldOP": 0.166667}, {"id": 887317, "card1": "K", "card2": "K", "card3": "A", "card4": "3", "doubleSuited": false, "goodSuit": false, "call": 0.166667, "raise": 0.333333, "raiseFoldIP": 0.333333, "raiseFoldOP": 0.333333}, {"id": 887322, "card1": "K", "card2": "K", "card3": "A", "card4": "3", "doubleSuited": false, "goodSuit": true, "call": 0.482582, "raise": 0.017418, "raiseFoldIP": 0.017418, "raiseFoldOP": 0.017418}, {"id": 887339, "card1": "K", "card2": "K", "card3": "A", "card4": "2", "doubleSuited": false, "goodSuit": false, "call": 0.148188, "raise": 0.351812, "raiseFoldIP": 0.351812, "raiseFoldOP": 0.351812}, {"id": 887345, "card1": "K", "card2": "K", "card3": "A", "card4": "2", "doubleSuited": false, "goodSuit": true, "call": 0.488676, "raise": 0.011324, "raiseFoldIP": 0.011324, "raiseFoldOP": 0.011324}, {"id": 887399, "card1": "K", "card2": "K", "card3": "A", "card4": "6", "doubleSuited": false, "goodSuit": true, "call": 0.000315, "raise": 0.499685, "raiseFoldIP": 0.499685, "raiseFoldOP": 0.499685}, {"id": 887415, "card1": "K", "card2": "K", "card3": "A", "card4": "5", "doubleSuited": false, "goodSuit": false, "call": 0.030119, "raise": 0.469881, "raiseFoldIP": 0.469881, "raiseFoldOP": 0.469881}, {"id": 887419, "card1": "K", "card2": "K", "card3": "A", "card4": "5", "doubleSuited": false, "goodSuit": true, "call": 0.052603, "raise": 0.447397, "raiseFoldIP": 0.447397, "raiseFoldOP": 0.447397}, {"id": 888560, "card1": "K", "card2": "K", "card3": "J", "card4": "J", "doubleSuited": false, "goodSuit": true, "call": 0.25}, {"id": 888593, "card1": "K", "card2": "K", "card3": "J", "card4": "T", "doubleSuited": false, "goodSuit": false, "call": 0.5}, {"id": 888598, "card1": "K", "card2": "K", "card3": "J", "card4": "T", "doubleSuited": false, "goodSuit": true, "call": 0.5}, {"id": 888719, "card1": "K", "card2": "K", "card3": "J", "card4": "5", "doubleSuited": false, "goodSuit": false, "call": 0.5}, {"id": 888723, "card1": "K", "card2": "K", "card3": "J", "card4": "5", "doubleSuited": false, "goodSuit": true, "call": 0.5}, {"id": 888747, "card1": "K", "card2": "K", "card3": "J", "card4": "4", "doubleSuited": false, "goodSuit": false, "call": 0.5}, {"id": 888752, "card1": "K", "card2": "K", "card3": "J", "card4": "4", "doubleSuited": false, "goodSuit": true, "call": 0.5}, {"id": 888769, "card1": "K", "card2": "K", "card3": "J", "card4": "3", "doubleSuited": false, "goodSuit": false, "call": 0.5}, {"id": 888775, "card1": "K", "card2": "K", "card3": "J", "card4": "3", "doubleSuited": false, "goodSuit": true, "call": 0.5}, {"id": 888800, "card1": "K", "card2": "K", "card3": "J", "card4": "2", "doubleSuited": false, "goodSuit": false, "call": 0.5}, {"id": 888806, "card1": "K", "card2": "K", "card3": "J", "card4": "2", "doubleSuited": false, "goodSuit": true, "call": 0.5}, {"id": 888849, "card1": "K", "card2": "K", "card3": "J", "card4": "9", "doubleSuited": false, "goodSuit": false, "call": 0.5}, {"id": 888856, "card1": "K", "card2": "K", "card3": "J", "card4": "9", "doubleSuited": false, "goodSuit": true, "call": 0.5}, {"id": 888870, "card1": "K", "card2": "K", "card3": "J", "card4": "8", "doubleSuited": false, "goodSuit": false, "call": 0.5}, {"id": 888876, "card1": "K", "card2": "K", "card3": "J", "card4": "8", "doubleSuited": false, "goodSuit": true, "call": 0.5}, {"id": 888909, "card1": "K", "card2": "K", "card3": "J", "card4": "7", "doubleSuited": false, "goodSuit": false, "call": 0.5}, {"id": 888914, "card1": "K", "card2": "K", "card3": "J", "card4": "7", "doubleSuited": false, "goodSuit": true, "call": 0.5}, {"id": 888928, "card1": "K", "card2": "K", "card3": "J", "card4": "6", "doubleSuited": false, "goodSuit": false, "call": 0.5}, {"id": 888934, "card1": "K", "card2": "K", "card3": "J", "card4": "6", "doubleSuited": false, "goodSuit": true, "call": 0.5}, {"id": 889256, "card1": "K", "card2": "K", "card3": "Q", "card4": "4", "doubleSuited": false, "goodSuit": false, "call": 0.5}, {"id": 889262, "card1": "K", "card2": "K", "card3": "Q", "card4": "4", "doubleSuited": false, "goodSuit": true, "call": 0.5}, {"id": 889293, "card1": "K", "card2": "K", "card3": "Q", "card4": "3", "doubleSuited": false, "goodSuit": false, "call": 0.5}, {"id": 889298, "card1": "K", "card2": "K", "card3": "Q", "card4": "3", "doubleSuited": false, "goodSuit": true, "call": 0.5}, {"id": 889340, "card1": "K", "card2": "K", "card3": "Q", "card4": "2", "doubleSuited": false, "goodSuit": false, "call": 0.5}, {"id": 889346, "card1": "K", "card2": "K", "card3": "Q", "card4": "2", "doubleSuited": false, "goodSuit": true, "call": 0.5}, {"id": 889360, "card1": "K", "card2": "K", "card3": "Q", "card4": "8", "doubleSuited": false, "goodSuit": false, "call": 0.5}, {"id": 889364, "card1": "K", "card2": "K", "card3": "Q", "card4": "8", "doubleSuited": false, "goodSuit": true, "call": 0.5}, {"id": 889377, "card1": "K", "card2": "K", "card3": "Q", "card4": "7", "doubleSuited": false, "goodSuit": false, "call": 0.5}, {"id": 889382, "card1": "K", "card2": "K", "card3": "Q", "card4": "7", "doubleSuited": false, "goodSuit": true, "call": 0.5}, {"id": 889406, "card1": "K", "card2": "K", "card3": "Q", "card4": "6", "doubleSuited": false, "goodSuit": false, "call": 0.5}, {"id": 889411, "card1": "K", "card2": "K", "card3": "Q", "card4": "6", "doubleSuited": false, "goodSuit": true, "call": 0.5}, {"id": 889438, "card1": "K", "card2": "K", "card3": "Q", "card4": "5", "doubleSuited": false, "goodSuit": false, "call": 0.5}, {"id": 889443, "card1": "K", "card2": "K", "card3": "Q", "card4": "5", "doubleSuited": false, "goodSuit": true, "call": 0.5}, {"id": 889502, "card1": "K", "card2": "K", "card3": "Q", "card4": "9", "doubleSuited": false, "goodSuit": false, "call": 0.5}, {"id": 889507, "card1": "K", "card2": "K", "card3": "Q", "card4": "9", "doubleSuited": false, "goodSuit": true, "call": 0.5}, {"id": 889695, "card1": "K", "card2": "K", "card3": "Q", "card4": "J", "doubleSuited": false, "goodSuit": false, "call": 0.5}, {"id": 889699, "card1": "K", "card2": "K", "card3": "Q", "card4": "J", "doubleSuited": false, "goodSuit": true, "call": 0.5}, {"id": 890109, "card1": "K", "card2": "K", "card3": "T", "card4": "3", "doubleSuited": false, "goodSuit": false, "call": 0.5}, {"id": 890113, "card1": "K", "card2": "K", "card3": "T", "card4": "3", "doubleSuited": false, "goodSuit": true, "call": 0.5}, {"id": 890129, "card1": "K", "card2": "K", "card3": "T", "card4": "2", "doubleSuited": false, "goodSuit": false, "call": 0.5}, {"id": 890132, "card1": "K", "card2": "K", "card3": "T", "card4": "2", "doubleSuited": false, "goodSuit": true, "call": 0.5}, {"id": 890149, "card1": "K", "card2": "K", "card3": "Q", "card4": "T", "doubleSuited": false, "goodSuit": false, "call": 0.5}, {"id": 890154, "card1": "K", "card2": "K", "card3": "Q", "card4": "T", "doubleSuited": false, "goodSuit": true, "call": 0.5}, {"id": 890168, "card1": "K", "card2": "K", "card3": "Q", "card4": "Q", "doubleSuited": false, "goodSuit": true, "call": 0.25}, {"id": 890246, "card1": "K", "card2": "K", "card3": "T", "card4": "T", "doubleSuited": false, "goodSuit": true, "call": 0.25}, {"id": 890261, "card1": "K", "card2": "K", "card3": "T", "card4": "7", "doubleSuited": false, "goodSuit": false, "call": 0.5}, {"id": 890265, "card1": "K", "card2": "K", "card3": "T", "card4": "7", "doubleSuited": false, "goodSuit": true, "call": 0.5}, {"id": 890278, "card1": "K", "card2": "K", "card3": "T", "card4": "6", "doubleSuited": false, "goodSuit": false, "call": 0.5}, {"id": 890283, "card1": "K", "card2": "K", "card3": "T", "card4": "6", "doubleSuited": false, "goodSuit": true, "call": 0.5}, {"id": 890295, "card1": "K", "card2": "K", "card3": "T", "card4": "5", "doubleSuited": false, "goodSuit": false, "call": 0.5}, {"id": 890300, "card1": "K", "card2": "K", "card3": "T", "card4": "5", "doubleSuited": false, "goodSuit": true, "call": 0.5}, {"id": 890322, "card1": "K", "card2": "K", "card3": "T", "card4": "4", "doubleSuited": false, "goodSuit": false, "call": 0.5}, {"id": 890326, "card1": "K", "card2": "K", "card3": "T", "card4": "4", "doubleSuited": false, "goodSuit": true, "call": 0.5}, {"id": 890341, "card1": "K", "card2": "K", "card3": "T", "card4": "9", "doubleSuited": false, "goodSuit": false, "call": 0.5}, {"id": 890346, "card1": "K", "card2": "K", "card3": "T", "card4": "9", "doubleSuited": false, "goodSuit": true, "call": 0.5}, {"id": 890356, "card1": "K", "card2": "K", "card3": "T", "card4": "8", "doubleSuited": false, "goodSuit": false, "call": 0.5}, {"id": 890361, "card1": "K", "card2": "K", "card3": "T", "card4": "8", "doubleSuited": false, "goodSuit": true, "call": 0.5}, {"id": 893874, "card1": "K", "card2": "K", "card3": "2", "card4": "2", "doubleSuited": false, "goodSuit": true, "call": 0.25}, {"id": 893884, "card1": "K", "card2": "K", "card3": "3", "card4": "2", "doubleSuited": false, "goodSuit": false, "call": 0.5}, {"id": 893888, "card1": "K", "card2": "K", "card3": "3", "card4": "2", "doubleSuited": false, "goodSuit": true, "call": 0.5}, {"id": 894013, "card1": "K", "card2": "K", "card3": "4", "card4": "4", "doubleSuited": false, "goodSuit": true, "call": 0.25}, {"id": 894046, "card1": "K", "card2": "K", "card3": "5", "card4": "4", "doubleSuited": false, "goodSuit": false, "call": 0.5}, {"id": 894048, "card1": "K", "card2": "K", "card3": "5", "card4": "4", "doubleSuited": false, "goodSuit": true, "call": 0.5}, {"id": 894063, "card1": "K", "card2": "K", "card3": "5", "card4": "3", "doubleSuited": false, "goodSuit": false, "call": 0.5}, {"id": 894065, "card1": "K", "card2": "K", "card3": "5", "card4": "3", "doubleSuited": false, "goodSuit": true, "call": 0.5}, {"id": 894088, "card1": "K", "card2": "K", "card3": "5", "card4": "2", "doubleSuited": false, "goodSuit": false, "call": 0.5}, {"id": 894091, "card1": "K", "card2": "K", "card3": "5", "card4": "2", "doubleSuited": false, "goodSuit": true, "call": 0.5}, {"id": 894121, "card1": "K", "card2": "K", "card3": "3", "card4": "3", "doubleSuited": false, "goodSuit": true, "call": 0.25}, {"id": 894150, "card1": "K", "card2": "K", "card3": "4", "card4": "3", "doubleSuited": false, "goodSuit": false, "call": 0.5}, {"id": 894153, "card1": "K", "card2": "K", "card3": "4", "card4": "3", "doubleSuited": false, "goodSuit": true, "call": 0.5}, {"id": 894162, "card1": "K", "card2": "K", "card3": "4", "card4": "2", "doubleSuited": false, "goodSuit": false, "call": 0.5}, {"id": 894165, "card1": "K", "card2": "K", "card3": "4", "card4": "2", "doubleSuited": false, "goodSuit": true, "call": 0.5}, {"id": 894825, "card1": "K", "card2": "K", "card3": "A", "card4": "8", "doubleSuited": false, "goodSuit": false, "raise": 0.5, "raiseFoldIP": 0.5, "raiseFoldOP": 0.5}, {"id": 894827, "card1": "K", "card2": "K", "card3": "A", "card4": "8", "doubleSuited": false, "goodSuit": true, "raise": 0.5, "raiseFoldIP": 0.5, "raiseFoldOP": 0.5}, {"id": 894844, "card1": "K", "card2": "K", "card3": "A", "card4": "7", "doubleSuited": false, "goodSuit": false, "raise": 0.5, "raiseFoldIP": 0.5, "raiseFoldOP": 0.5}, {"id": 894846, "card1": "K", "card2": "K", "card3": "A", "card4": "7", "doubleSuited": false, "goodSuit": true, "raise": 0.5, "raiseFoldIP": 0.5, "raiseFoldOP": 0.5}, {"id": 894859, "card1": "K", "card2": "K", "card3": "A", "card4": "6", "doubleSuited": false, "goodSuit": false, "raise": 0.5, "raiseFoldIP": 0.5, "raiseFoldOP": 0.5}, {"id": 894882, "card1": "K", "card2": "K", "card3": "A", "card4": "9", "doubleSuited": false, "goodSuit": false, "raise": 0.5, "raiseFoldIP": 0.5, "raiseFoldOP": 0.5}, {"id": 894886, "card1": "K", "card2": "K", "card3": "A", "card4": "9", "doubleSuited": false, "goodSuit": true, "raise": 0.5, "raiseFoldIP": 0.5, "raiseFoldOP": 0.5}, {"id": 895061, "card1": "K", "card2": "K", "card3": "A", "card4": "J", "doubleSuited": false, "goodSuit": false, "raise": 0.5, "raiseFoldIP": 0.5, "raiseFoldOP": 0.5}, {"id": 895063, "card1": "K", "card2": "K", "card3": "A", "card4": "J", "doubleSuited": false, "goodSuit": true, "raise": 0.5, "raiseFoldIP": 0.5, "raiseFoldOP": 0.5}, {"id": 895069, "card1": "K", "card2": "K", "card3": "A", "card4": "T", "doubleSuited": false, "goodSuit": false, "raise": 0.5, "raiseFoldIP": 0.5, "raiseFoldOP": 0.5}, {"id": 895072, "card1": "K", "card2": "K", "card3": "A", "card4": "T", "doubleSuited": false, "goodSuit": true, "raise": 0.5, "raiseFoldIP": 0.5, "raiseFoldOP": 0.5}, {"id": 895081, "card1": "K", "card2": "K", "card3": "A", "card4": "Q", "doubleSuited": false, "goodSuit": false, "raise": 0.5, "raiseFoldIP": 0.5, "raiseFoldOP": 0.5}, {"id": 895084, "card1": "K", "card2": "K", "card3": "A", "card4": "Q", "doubleSuited": false, "goodSuit": true, "raise": 0.5, "raiseFoldIP": 0.5, "raiseFoldOP": 0.5}]